sinkhorn_router_pytorch/__init__.py
sinkhorn_router_pytorch/sinkhorn_router.py
sinkhorn_router_pytorch/switchhead.py
sinkhorn_router_pytorch-0.0.14.dist-info/METADATA
sinkhorn_router_pytorch-0.0.14.dist-info/WHEEL
sinkhorn_router_pytorch-0.0.14.dist-info/licenses/LICENSE
sinkhorn_router_pytorch-0.0.14.dist-info/RECORD
