Metadata-Version: 2.3
Name: sinkhorn-router-pytorch
Version: 0.0.14
Summary: Sinkhorn Router - Pytorch
Project-URL: Homepage, https://pypi.org/project/sinkhorn-router-pytorch/
Project-URL: Repository, https://github.com/lucidrains/sinkhorn-router-pytorch
Author-email: Phil Wang <lucidrains@gmail.com>
License: MIT License
License-File: LICENSE
Keywords: artificial intelligence,deep learning,mixture of experts,routing
Classifier: Development Status :: 4 - Beta
Classifier: Intended Audience :: Developers
Classifier: License :: OSI Approved :: MIT License
Classifier: Programming Language :: Python :: 3.9
Classifier: Topic :: Scientific/Engineering :: Artificial Intelligence
Requires-Python: >=3.9
Requires-Dist: einops>=0.8.0
Requires-Dist: einx>=0.3.0
Requires-Dist: torch>=2.0
Provides-Extra: examples
Provides-Extra: test
Requires-Dist: pytest; extra == 'test'
